README.md
setup.py
apprunner/__init__.py
apprunner/exceptions.py
apprunner/factory.py
apprunner/runner.py
apprunner.egg-info/PKG-INFO
apprunner.egg-info/SOURCES.txt
apprunner.egg-info/dependency_links.txt
apprunner.egg-info/top_level.txt
samples/__init__.py
samples/demo.py
tests/__init__.py